cpskin.citizen-1.4.2-py2.7-nspkg.pth
cpskin/citizen/__init__.py
cpskin/citizen/adapter.py
cpskin/citizen/behavior.py
cpskin/citizen/configure.zcml
cpskin/citizen/indexers.py
cpskin/citizen/interfaces.py
cpskin/citizen/localrole.py
cpskin/citizen/monkey.zcml
cpskin/citizen/monkeypatches.py
cpskin/citizen/notification.py
cpskin/citizen/permissions.py
cpskin/citizen/permissions.zcml
cpskin/citizen/security.py
cpskin/citizen/setuphandlers.py
cpskin/citizen/subscriber.py
cpskin/citizen/testing.py
cpskin/citizen/testing.zcml
cpskin/citizen/upgradehandlers.py
cpskin/citizen/upgrades.zcml
cpskin/citizen/user.py
cpskin/citizen/utils.py
cpskin/citizen/vocabularies.py
cpskin/citizen/vocabularies.zcml
cpskin/citizen/browser/__init__.py
cpskin/citizen/browser/cancel.py
cpskin/citizen/browser/citizen_first_login.py
cpskin/citizen/browser/claim.py
cpskin/citizen/browser/configure.zcml
cpskin/citizen/browser/control.py
cpskin/citizen/browser/edit.py
cpskin/citizen/browser/iterate.py
cpskin/citizen/browser/propose.py
cpskin/citizen/browser/settings.py
cpskin/citizen/browser/tools.py
cpskin/citizen/browser/validation.py
cpskin/citizen/browser/viewlets.py
cpskin/citizen/browser/resources/citizen.css
cpskin/citizen/browser/templates/citizen-admin-viewlet.pt
cpskin/citizen/browser/templates/citizen-cancel.pt
cpskin/citizen/browser/templates/citizen-claim.pt
cpskin/citizen/browser/templates/citizen-edition-viewlet.pt
cpskin/citizen/browser/templates/citizen-propose-viewlet.pt
cpskin/citizen/browser/templates/citizen-return-checkout.pt
cpskin/citizen/browser/templates/citizen-validation-required.pt
cpskin/citizen/browser/templates/fix_links.pt
cpskin/citizen/browser/templates/propose-citizen.pt
cpskin/citizen/browser/templates/security_migrator.pt
cpskin/citizen/browser/tests/__init__.py
cpskin/citizen/browser/tests/test_cancel.py
cpskin/citizen/dashboard/__init__.py
cpskin/citizen/dashboard/actions.py
cpskin.citizen-1.4.2.dist-info/DESCRIPTION.rst
cpskin.citizen-1.4.2.dist-info/METADATA
cpskin.citizen-1.4.2.dist-info/RECORD
cpskin.citizen-1.4.2.dist-info/WHEEL
cpskin.citizen-1.4.2.dist-info/entry_points.txt
cpskin.citizen-1.4.2.dist-info/metadata.json
cpskin.citizen-1.4.2.dist-info/namespace_packages.txt
cpskin.citizen-1.4.2.dist-info/top_level.txt
