Metadata-Version: 2.0
Name: cpskin.citizen
Version: 1.4.2
Summary: An add-on for Plone
Home-page: https://pypi.python.org/pypi/cpskin.citizen
Author: Martin Peeters
Author-email: martin.peeters@affinitic.be
License: GPL version 2
Keywords: Python Plone
Platform: UNKNOWN
Classifier: Environment :: Web Environment
Classifier: Framework :: Plone
Classifier: Framework :: Plone :: 4.3
Classifier: Programming Language :: Python
Classifier: Programming Language :: Python :: 2.7
Classifier: Operating System :: OS Independent
Classifier: License :: OSI Approved :: GNU General Public License v2 (GPLv2)
Provides-Extra: test
Requires-Dist: borg.localrole
Requires-Dist: collective.geo.leaflet
Requires-Dist: collective.monkeypatcher
Requires-Dist: collective.z3cform.select2
Requires-Dist: imio.dashboard
Requires-Dist: plone.api
Requires-Dist: plone.app.contenttypes
Requires-Dist: plone.app.dexterity
Requires-Dist: plone.app.iterate
Requires-Dist: plone.app.stagingbehavior
Requires-Dist: plone.principalsource
Requires-Dist: setuptools
Requires-Dist: z3c.jbot
Requires-Dist: geocoder
Provides-Extra: test
Requires-Dist: collective.contact.core; extra == 'test'
Requires-Dist: plone.app.testing; extra == 'test'
Requires-Dist: plone.app.contenttypes; extra == 'test'
Requires-Dist: plone.app.robotframework[debug]; extra == 'test'
Requires-Dist: Mock; extra == 'test'
